py_eth_contract/__init__.py
py_eth_contract/contract_utils.py
py_eth_contract/exceptions.py
py_eth_contract/wrapped_contract.py
py_eth_contract-0.1.1.dist-info/METADATA
py_eth_contract-0.1.1.dist-info/WHEEL
py_eth_contract-0.1.1.dist-info/RECORD
